nonebot_plugin_bilimusic/__init__.py
nonebot_plugin_bilimusic/config.py
nonebot_plugin_bilimusic/downloader.py
nonebot_plugin_bilimusic/utils.py
nonebot_plugin_bilimusic-1.1.1.dist-info/LICENSE
nonebot_plugin_bilimusic-1.1.1.dist-info/METADATA
nonebot_plugin_bilimusic-1.1.1.dist-info/WHEEL
nonebot_plugin_bilimusic-1.1.1.dist-info/RECORD
