Metadata-Version: 2.1
Name: nonebot_plugin_bilimusic
Version: 1.1.1
Summary: 一款基于 Nonebot2 的 Bilibili 视频提取音乐和歌词插件。
Home-page: https://github.com/Lonely-Sails/nonebot-plugin-bilimusic
License: GPL3
Keywords: nonebot,nonebot2,bilibili,music,lyric
Author: Lonely-Sails
Requires-Python: >=3.8,<4.0
Classifier: License :: Other/Proprietary License
Classifier: Programming Language :: Python :: 3
Classifier: Programming Language :: Python :: 3.8
Classifier: Programming Language :: Python :: 3.9
Classifier: Programming Language :: Python :: 3.10
Classifier: Programming Language :: Python :: 3.11
Classifier: Programming Language :: Python :: 3.12
Requires-Dist: httpx (>=0.24.1,<0.25.0)
Requires-Dist: nonebot-adapter-onebot (>=2.4.3,<3.0.0)
Requires-Dist: nonebot2 (>=2.2.0,<3.0.0)
Project-URL: Documentation, https://github.com/Lonely-Sails/nonebot-plugin-bilimusic#readme
Project-URL: Repository, https://github.com/Lonely-Sails/nonebot-plugin-bilimusic
